emccd_detect/__init__.py
emccd_detect/cosmics.py
emccd_detect/emccd_detect.py
emccd_detect/nonlinearity.py
emccd_detect/rand_em_gain.py
emccd_detect/util/__init__.py
emccd_detect/util/metadata.yaml
emccd_detect/util/read_metadata.py
emccd_detect/util/read_metadata_wrapper.py
emccd_detect-2.5.0.dist-info/licenses/LICENSE.txt
emccd_detect-2.5.0.dist-info/METADATA
emccd_detect-2.5.0.dist-info/WHEEL
emccd_detect-2.5.0.dist-info/top_level.txt
emccd_detect-2.5.0.dist-info/RECORD
