Metadata-Version: 2.4
Name: emccd_detect
Version: 2.5.0
Summary: EMCCD detector image simulation
Author-email: Bijan Nemati <bijan.nemati@tellus1.com>, Sam Miller <sam.miller@uah.edu>, Kevin Ludwick <kevin.ludwick@uah.edu>
Classifier: Development Status :: 4 - Beta
Classifier: Intended Audience :: Developers
Classifier: Programming Language :: Python :: 3
Requires-Python: >=3.6
License-File: LICENSE.txt
Requires-Dist: astropy
Requires-Dist: matplotlib
Requires-Dist: numpy
Requires-Dist: scipy
Requires-Dist: pynufft==2020.0.0
Requires-Dist: pyyaml
Dynamic: license-file
